Es/BugReporter.py
Es/DataAnalysis.py
Es/WebGeter.py
Es/__init__.py
Emeraldspray-1.2.2.dist-info/LICENSE
Emeraldspray-1.2.2.dist-info/METADATA
Emeraldspray-1.2.2.dist-info/WHEEL
Emeraldspray-1.2.2.dist-info/top_level.txt
Emeraldspray-1.2.2.dist-info/RECORD
