Metadata-Version: 2.1
Name: Emeraldspray
Version: 1.2.2
Summary: 方便的将steam商店页面信息解析出来，并保存到本地
Home-page: https://github.com/fred0m/Emerald-spray
Author: fredom
Author-email: he@fredom.ink
License: UNKNOWN
Platform: UNKNOWN
Requires-Dist: requests
Requires-Dist: BeautifulSoup4
